Metadata-Version: 2.1
Name: byted-overpass-oec-governance-sentry-namelist-rpc
Version: 0.0.1
Summary: A simple package named byted_overpass_oec_governance_sentry_namelist_rpc
Home-page: https://github.com/artifact/byted_overpass_oec_governance_sentry_namelist_rpc.git
Author: artifact
Author-email: artifact@example.com
License: UNKNOWN
Platform: UNKNOWN
Classifier: Programming Language :: Python :: 3
Classifier: License :: OSI Approved :: MIT License
Classifier: Operating System :: OS Independent
